LICENSE
README.md
setup.cfg
setup.py
morphtransformkun/__init__.py
morphtransformkun/morphtransformkun.py
morphtransformkun.egg-info/PKG-INFO
morphtransformkun.egg-info/SOURCES.txt
morphtransformkun.egg-info/dependency_links.txt
morphtransformkun.egg-info/not-zip-safe
morphtransformkun.egg-info/requires.txt
morphtransformkun.egg-info/top_level.txt