Metadata-Version: 2.1
Name: morphtransformkun
Version: 0.0.9
Summary: A python package for morphological transformations on image
Home-page: https://github.com/ankalagigaurave/morphtransformkun-Package
Author: Gaurav Ankalagi
License: MIT
Platform: UNKNOWN
License-File: LICENSE
